setup.py
will/__init__.py
will/data/#send#
will/data/get
will/data/get~
will/data/send
will/data/send~
wyatt.egg-info/PKG-INFO
wyatt.egg-info/SOURCES.txt
wyatt.egg-info/dependency_links.txt
wyatt.egg-info/requires.txt
wyatt.egg-info/top_level.txt