Metadata-Version: 1.1
Name: wyatt
Version: 0.1.19
Summary: A way to talk to will wyatt.
Home-page: https://iex.ist
Author: wyatt
Author-email: goFuck@your.self
License: UNKNOWN
Platform: UNKNOWN
Classifier: Development Status :: 3 - Alpha
Classifier: Environment :: Console
Classifier: Intended Audience :: End Users/Desktop
Classifier: Intended Audience :: System Administrators
Classifier: License :: OSI Approved :: Python Software Foundation License
Classifier: Operating System :: MacOS :: MacOS X
Classifier: Programming Language :: Python
Classifier: Topic :: Communications :: Email
